Metadata-Version: 2.1
Name: pyzipcode
Version: 3.0.0
Summary: query zip codes and location data
Home-page: https://github.com/vangheem/pyzipcode
Author: Nathan Van Gheem
Author-email: vangheem@gmail.com
License: MIT
Keywords: zip code distance
Platform: UNKNOWN
Classifier: Programming Language :: Python :: 3
Classifier: License :: OSI Approved :: MIT License
Classifier: Operating System :: OS Independent
Requires-Python: >=3.3
